{"t":1768634860,"a":19.7,"tg":21,"d":-1.3,"tr":0,"ed":-1.3,"sb":19.5,"sa":19.5,"sp":0,"p":1,"l":93,"tf":2,"mp":70}
{"t":1768634880,"a":19.7,"tg":21,"d":-1.3,"tr":0,"ed":-1.3,"sb":19.5,"sa":19.5,"sp":0,"p":1,"l":93,"tf":2,"mp":70}
{"t":1768634900,"a":19.7,"tg":21,"d":-1.3,"tr":0.1,"ed":-1.1,"sb":19.5,"sa":19.5,"sp":0,"p":1,"l":93,"tf":2,"mp":70}
{"t":1768634920,"a":19.7,"tg":21,"d":-1.3,"tr":0.1,"ed":-1.1,"sb":19.5,"sa":19.5,"sp":0,"p":1,"l":93,"tf":2,"mp":70}
{"t":1768634940,"a":19.7,"tg":21,"d":-1.3,"tr":0.1,"ed":-1.1,"sb":19.5,"sa":19.5,"sp":0,"p":1,"l":93,"tf":2,"mp":70}
{"t":1768634960,"a":19.7,"tg":21,"d":-1.3,"tr":0.1,"ed":-1.1,"sb":19.5,"sa":19.5,"sp":0,"p":1,"l":93,"tf":2,"mp":70}
{"t":1768634980,"a":19.7,"tg":21,"d":-1.3,"tr":0.1,"ed":-1.1,"sb":19.5,"sa":19.5,"sp":0,"p":1,"l":93,"tf":2,"mp":70}
{"t":1768635000,"a":19.7,"tg":21,"d":-1.3,"tr":0.1,"ed":-1.1,"sb":19.5,"sa":19.5,"sp":0,"p":1,"l":93,"tf":2,"mp":70}
{"t":1768635020,"a":19.7,"tg":21,"d":-1.3,"tr":0.1,"ed":-1.1,"sb":19.5,"sa":19.5,"sp":0,"p":1,"l":93,"tf":2,"mp":70}
{"t":1768635040,"a":19.7,"tg":21,"d":-1.3,"tr":0.1,"ed":-1.1,"sb":19.5,"sa":19.5,"sp":0,"p":1,"l":93,"tf":2,"mp":70}
{"t":1768635060,"a":19.7,"tg":21,"d":-1.3,"tr":0.1,"ed":-1.1,"sb":19.5,"sa":19.5,"sp":0,"p":1,"l":93,"tf":2,"mp":70}
{"t":1768635080,"a":19.7,"tg":21,"d":-1.3,"tr":0.1,"ed":-1.1,"sb":19.5,"sa":19.5,"sp":0,"p":1,"l":93,"tf":2,"mp":70}
{"t":1768635100,"a":19.7,"tg":21,"d":-1.3,"tr":0.1,"ed":-1.1,"sb":19.5,"sa":19.5,"sp":0,"p":1,"l":93,"tf":2,"mp":70}
{"t":1768635120,"a":19.7,"tg":21,"d":-1.3,"tr":0.1,"ed":-1.1,"sb":19.5,"sa":19.5,"sp":0,"p":1,"l":93,"tf":2,"mp":70}
{"t":1768635140,"a":19.7,"tg":21,"d":-1.3,"tr":0.1,"ed":-1.1,"sb":19.5,"sa":19.5,"sp":0,"p":1,"l":93,"tf":2,"mp":70}
{"t":1768635160,"a":19.9,"tg":21,"d":-1.1,"tr":0.1,"ed":-0.9,"sb":19.5,"sa":19.5,"sp":0,"p":1,"l":93,"tf":2,"mp":60}
{"t":1768635180,"a":19.9,"tg":21,"d":-1.1,"tr":0.1,"ed":-0.9,"sb":19.5,"sa":19.5,"sp":0,"p":1,"l":93,"tf":2,"mp":60}
{"t":1768635200,"a":19.9,"tg":21,"d":-1.1,"tr":0.3,"ed":-0.5,"sb":19.5,"sa":19,"sp":0,"p":1,"l":93,"tf":2,"mp":60}
{"t":1768635220,"a":19.9,"tg":21,"d":-1.1,"tr":0.3,"ed":-0.5,"sb":19,"sa":19,"sp":0,"p":1,"l":96,"tf":2,"mp":60}
{"t":1768635240,"a":19.9,"tg":21,"d":-1.1,"tr":0.3,"ed":-0.5,"sb":19,"sa":19,"sp":0,"p":1,"l":96,"tf":2,"mp":60}
{"t":1768635260,"a":19.9,"tg":21,"d":-1.1,"tr":0.3,"ed":-0.5,"sb":19,"sa":20,"sp":0,"p":1,"l":96,"tf":2,"mp":60}
{"t":1768635280,"a":19.9,"tg":21,"d":-1.1,"tr":0.3,"ed":-0.5,"sb":20,"sa":20,"sp":0,"p":1,"l":96,"tf":2,"mp":60}
{"t":1768635300,"a":19.9,"tg":21,"d":-1.1,"tr":0.3,"ed":-0.5,"sb":20,"sa":20,"sp":0,"p":1,"l":96,"tf":2,"mp":60}
{"t":1768635320,"a":19.9,"tg":21,"d":-1.1,"tr":0.3,"ed":-0.5,"sb":20,"sa":20,"sp":0,"p":1,"l":96,"tf":2,"mp":60}
{"t":1768635340,"a":19.9,"tg":21,"d":-1.1,"tr":0.3,"ed":-0.5,"sb":20,"sa":20,"sp":0,"p":1,"l":96,"tf":2,"mp":60}
{"t":1768635360,"a":19.9,"tg":21,"d":-1.1,"tr":0.3,"ed":-0.5,"sb":20,"sa":20,"sp":0,"p":1,"l":96,"tf":2,"mp":60}
{"t":1768635380,"a":19.9,"tg":21,"d":-1.1,"tr":0.2,"ed":-0.7,"sb":20,"sa":20,"sp":0,"p":1,"l":96,"tf":2,"mp":60}
{"t":1768635400,"a":19.9,"tg":21,"d":-1.1,"tr":0.2,"ed":-0.7,"sb":20,"sa":20,"sp":0,"p":1,"l":96,"tf":2,"mp":60}
{"t":1768635420,"a":19.9,"tg":21,"d":-1.1,"tr":0.2,"ed":-0.7,"sb":20,"sa":20,"sp":0,"p":1,"l":96,"tf":2,"mp":60}
{"t":1768635440,"a":19.9,"tg":21,"d":-1.1,"tr":0.2,"ed":-0.7,"sb":20,"sa":20,"sp":0,"p":1,"l":96,"tf":2,"mp":60}
{"t":1768635460,"a":19.7,"tg":21,"d":-1.3,"tr":0.2,"ed":-0.9,"sb":20,"sa":20.5,"sp":0,"p":1,"l":93,"tf":2,"mp":70}
{"t":1768635480,"a":19.7,"tg":21,"d":-1.3,"tr":0.2,"ed":-0.9,"sb":20.5,"sa":20.5,"sp":0,"p":1,"l":93,"tf":2,"mp":70}
{"t":1768635500,"a":19.7,"tg":21,"d":-1.3,"tr":0,"ed":-1.3,"sb":20.5,"sa":20.5,"sp":0,"p":1,"l":93,"tf":2,"mp":70}
{"t":1768635520,"a":19.7,"tg":21,"d":-1.3,"tr":0,"ed":-1.3,"sb":20.5,"sa":20.5,"sp":0,"p":1,"l":93,"tf":2,"mp":70}
{"t":1768635540,"a":19.7,"tg":21,"d":-1.3,"tr":0,"ed":-1.3,"sb":20.5,"sa":20.5,"sp":0,"p":1,"l":93,"tf":2,"mp":70}
{"t":1768635560,"a":19.7,"tg":21,"d":-1.3,"tr":0,"ed":-1.3,"sb":20.5,"sa":20.5,"sp":0,"p":1,"l":93,"tf":2,"mp":70}
{"t":1768635580,"a":19.7,"tg":21,"d":-1.3,"tr":0,"ed":-1.3,"sb":20.5,"sa":20.5,"sp":0,"p":1,"l":93,"tf":2}
{"t":1768635600,"a":19.7,"tg":21,"d":-1.3,"tr":0,"ed":-1.3,"sb":20.5,"sa":20.5,"sp":0,"p":1,"l":93,"tf":2}
{"t":1768635620,"a":19.7,"tg":21,"d":-1.3,"tr":-0.1,"ed":-1.5,"sb":20.5,"sa":21,"sp":0,"p":1,"l":90,"tf":2}
{"t":1768635640,"a":19.7,"tg":21,"d":-1.3,"tr":-0.1,"ed":-1.5,"sb":21,"sa":21,"sp":0,"p":1,"l":90,"tf":2}
{"t":1768635660,"a":19.5,"tg":21,"d":-1.5,"tr":-0.1,"ed":-1.7,"sb":21,"sa":22,"sp":0,"p":1,"l":90,"tf":2}
{"t":1768635680,"a":19.5,"tg":21,"d":-1.5,"tr":-0.3,"ed":-2.1,"sb":22,"sa":22,"sp":0,"p":1,"l":90,"tf":2}
{"t":1768635700,"a":19.5,"tg":21,"d":-1.5,"tr":-0.3,"ed":-2.1,"sb":22,"sa":22,"sp":0,"p":1,"l":90,"tf":2}
{"t":1768635720,"a":19.5,"tg":21,"d":-1.5,"tr":-0.3,"ed":-2.1,"sb":22,"sa":22,"sp":0,"p":1,"l":90,"tf":2}
{"t":1768635740,"a":19.5,"tg":21,"d":-1.5,"tr":-0.3,"ed":-2.1,"sb":22,"sa":22,"sp":0,"p":1,"l":90,"tf":2}
{"t":1768635760,"a":19.5,"tg":21,"d":-1.5,"tr":-0.3,"ed":-2.1,"sb":22,"sa":22,"sp":0,"p":1,"l":90,"tf":2}
{"t":1768635780,"a":19.5,"tg":21,"d":-1.5,"tr":-0.3,"ed":-2.1,"sb":22,"sa":22,"sp":0,"p":1,"l":90,"tf":2}
{"t":1768635800,"a":19.5,"tg":21,"d":-1.5,"tr":-0.2,"ed":-1.9,"sb":22,"sa":22,"sp":0,"p":1,"l":90,"tf":2}
{"t":1768635820,"a":19.5,"tg":21,"d":-1.5,"tr":-0.2,"ed":-1.9,"sb":22,"sa":22,"sp":0,"p":1,"l":90,"tf":2}
{"t":1768635840,"a":19.5,"tg":21,"d":-1.5,"tr":-0.2,"ed":-1.9,"sb":22,"sa":22,"sp":0,"p":1,"l":90,"tf":2}
{"t":1768635860,"a":19.5,"tg":21,"d":-1.5,"tr":-0.2,"ed":-1.9,"sb":22,"sa":22,"sp":0,"p":1,"l":90,"tf":2}
{"t":1768635880,"a":19.5,"tg":21,"d":-1.5,"tr":-0.2,"ed":-1.9,"sb":22,"sa":22,"sp":0,"p":1,"l":90,"tf":2}
{"t":1768635900,"a":19.5,"tg":21,"d":-1.5,"tr":-0.2,"ed":-1.9,"sb":22,"sa":22,"sp":0,"p":1,"l":90,"tf":2}
{"t":1768635920,"a":19.5,"tg":21,"d":-1.5,"tr":-0.2,"ed":-1.9,"sb":22,"sa":22,"sp":0,"p":1,"l":90,"tf":2}
{"t":1768635940,"a":19.5,"tg":21,"d":-1.5,"tr":-0.2,"ed":-1.9,"sb":22,"sa":22,"sp":0,"p":1,"l":90,"tf":2}
{"t":1768635960,"a":19.5,"tg":21,"d":-1.5,"tr":-0.2,"ed":-1.9,"sb":22,"sa":22,"sp":0,"p":1,"l":90,"tf":2}
{"t":1768635980,"a":19.7,"tg":21,"d":-1.3,"tr":-0.2,"ed":-1.7,"sb":22,"sa":22,"sp":0,"p":1,"l":90,"tf":2}
{"t":1768636000,"a":19.7,"tg":21,"d":-1.3,"tr":-0.2,"ed":-1.7,"sb":22,"sa":22,"sp":0,"p":1,"l":90,"tf":2}
{"t":1768636020,"a":19.7,"tg":21,"d":-1.3,"tr":-0.2,"ed":-1.7,"sb":22,"sa":22,"sp":0,"p":1,"l":90,"tf":2}
{"t":1768636040,"a":19.7,"tg":21,"d":-1.3,"tr":0,"ed":-1.3,"sb":22,"sa":21.5,"sp":0,"p":1,"l":93,"tf":2}
{"t":1768636060,"a":19.7,"tg":21,"d":-1.3,"tr":0,"ed":-1.3,"sb":21.5,"sa":21.5,"sp":0,"p":1,"l":93,"tf":2}
{"t":1768636080,"a":19.7,"tg":21,"d":-1.3,"tr":0,"ed":-1.3,"sb":21.5,"sa":21.5,"sp":0,"p":1,"l":93,"tf":2}
{"t":1768636100,"a":19.7,"tg":21,"d":-1.3,"tr":0,"ed":-1.3,"sb":21.5,"sa":21.5,"sp":0,"p":1,"l":93,"tf":2}
{"t":1768636120,"a":19.7,"tg":21,"d":-1.3,"tr":0,"ed":-1.3,"sb":21.5,"sa":21.5,"sp":0,"p":1,"l":93,"tf":2}
{"t":1768636140,"a":19.7,"tg":21,"d":-1.3,"tr":0,"ed":-1.3,"sb":21.5,"sa":21.5,"sp":0,"p":1,"l":93,"tf":2}
{"t":1768636160,"a":19.7,"tg":21,"d":-1.3,"tr":0,"ed":-1.3,"sb":21.5,"sa":21.5,"sp":0,"p":1,"l":93,"tf":2}
{"t":1768636180,"a":19.7,"tg":21,"d":-1.3,"tr":0,"ed":-1.3,"sb":21.5,"sa":21.5,"sp":0,"p":1,"l":93,"tf":2}
{"t":1768636200,"a":19.9,"tg":21,"d":-1.1,"tr":0,"ed":-1.1,"sb":21.5,"sa":21.5,"sp":0,"p":1,"l":93,"tf":2}
{"t":1768636220,"a":19.9,"tg":21,"d":-1.1,"tr":0.2,"ed":-0.7,"sb":21.5,"sa":"21","sp":0,"p":1,"l":96,"tf":2}
{"t":1768636240,"a":19.9,"tg":21,"d":-1.1,"tr":0.2,"ed":-0.7,"sb":21,"sa":"21","sp":0,"p":1,"l":96,"tf":2}
{"t":1768636260,"a":19.9,"tg":21,"d":-1.1,"tr":0.2,"ed":-0.7,"sb":21,"sa":"21","sp":0,"p":1,"l":96,"tf":2}
{"t":1768636280,"a":19.9,"tg":21,"d":-1.1,"tr":0.2,"ed":-0.7,"sb":21,"sa":"21","sp":0,"p":1,"l":96,"tf":2}
{"t":1768636300,"a":19.9,"tg":21,"d":-1.1,"tr":0.2,"ed":-0.7,"sb":21,"sa":"21","sp":0,"p":1,"l":96,"tf":2}
{"t":1768636320,"a":19.9,"tg":21,"d":-1.1,"tr":0.2,"ed":-0.7,"sb":21,"sa":"21","sp":0,"p":1,"l":96,"tf":2}
{"t":1768636340,"a":19.9,"tg":21,"d":-1.1,"tr":0.2,"ed":-0.7,"sb":21,"sa":"21","sp":0,"p":1,"l":96,"tf":2}
{"t":1768636360,"a":19.9,"tg":21,"d":-1.1,"tr":0.2,"ed":-0.7,"sb":21,"sa":"21","sp":0,"p":1,"l":96,"tf":2}
{"t":1768636380,"a":19.9,"tg":21,"d":-1.1,"tr":0.2,"ed":-0.7,"sb":21,"sa":"21","sp":0,"p":1,"l":96,"tf":2}
{"t":1768636400,"a":19.9,"tg":21,"d":-1.1,"tr":0.2,"ed":-0.7,"sb":21,"sa":"21","sp":0,"p":1,"l":96,"tf":2}
{"t":1768636420,"a":19.9,"tg":21,"d":-1.1,"tr":0.2,"ed":-0.7,"sb":21,"sa":"21","sp":0,"p":1,"l":96,"tf":2}
{"t":1768636440,"a":19.9,"tg":21,"d":-1.1,"tr":0.2,"ed":-0.7,"sb":21,"sa":"21","sp":0,"p":1,"l":96,"tf":2}
{"t":1768636460,"a":19.9,"tg":21,"d":-1.1,"tr":0.2,"ed":-0.7,"sb":21,"sa":"21","sp":0,"p":1,"l":96,"tf":2}
{"t":1768636480,"a":19.9,"tg":21,"d":-1.1,"tr":0.2,"ed":-0.7,"sb":21,"sa":"21","sp":0,"p":1,"l":96,"tf":2}
{"t":1768636500,"a":19.9,"tg":21,"d":-1.1,"tr":0.2,"ed":-0.7,"sb":21,"sa":"21","sp":0,"p":1,"l":96,"tf":2}
{"t":1768636520,"a":19.9,"tg":21,"d":-1.1,"tr":0.2,"ed":-0.7,"sb":21,"sa":"21","sp":0,"p":1,"l":96,"tf":2}
{"t":1768636540,"a":19.9,"tg":21,"d":-1.1,"tr":0.2,"ed":-0.7,"sb":21,"sa":"21","sp":0,"p":1,"l":96,"tf":2}
{"t":1768636560,"a":19.9,"tg":21,"d":-1.1,"tr":0.2,"ed":-0.7,"sb":21,"sa":"21","sp":0,"p":1,"l":96,"tf":2}
{"t":1768636580,"a":19.9,"tg":21,"d":-1.1,"tr":0.2,"ed":-0.7,"sb":21,"sa":"21","sp":0,"p":1,"l":96,"tf":2}
{"t":1768636600,"a":19.9,"tg":21,"d":-1.1,"tr":0.2,"ed":-0.7,"sb":21,"sa":"21","sp":0,"p":1,"l":96,"tf":2}
{"t":1768636620,"a":20.1,"tg":21,"d":-0.9,"tr":0.2,"ed":-0.5,"sb":21,"sa":"21","sp":0,"p":1,"l":96,"tf":2}
{"t":1768636640,"a":20.1,"tg":21,"d":-0.9,"tr":0.4,"ed":-0.1,"sb":21,"sa":"21","sp":-1,"p":1,"l":99,"tf":2}
{"t":1768636660,"a":20.1,"tg":21,"d":-0.9,"tr":0.4,"ed":-0.1,"sb":21,"sa":"21","sp":-1,"p":1,"l":99,"tf":2}
{"t":1768636680,"a":20.1,"tg":21,"d":-0.9,"tr":0.4,"ed":-0.1,"sb":21,"sa":"21","sp":-1,"p":1,"l":99,"tf":2}
{"t":1768636700,"a":20.1,"tg":21,"d":-0.9,"tr":0.3,"ed":-0.3,"sb":21,"sa":"21","sp":-1,"p":1,"l":99,"tf":2}
{"t":1768636720,"a":20.1,"tg":21,"d":-0.9,"tr":0.3,"ed":-0.3,"sb":21,"sa":"21","sp":-1,"p":1,"l":99,"tf":2}
{"t":1768636740,"a":20.1,"tg":21,"d":-0.9,"tr":0.3,"ed":-0.3,"sb":21,"sa":"21","sp":-1,"p":1,"l":99,"tf":2}
{"t":1768636760,"a":20.1,"tg":21,"d":-0.9,"tr":0.3,"ed":-0.3,"sb":21,"sa":"21","sp":-1,"p":1,"l":99,"tf":2}
{"t":1768636780,"a":20.1,"tg":21,"d":-0.9,"tr":0.3,"ed":-0.3,"sb":21,"sa":"21","sp":-1,"p":1,"l":99,"tf":2}
{"t":1768636800,"a":20.1,"tg":21,"d":-0.9,"tr":0.3,"ed":-0.3,"sb":21,"sa":"21","sp":-1,"p":1,"l":99,"tf":2}
{"t":1768636820,"a":20.1,"tg":21,"d":-0.9,"tr":0.3,"ed":-0.3,"sb":21,"sa":"21","sp":-1,"p":1,"l":99,"tf":2}
{"t":1768636840,"a":20.1,"tg":21,"d":-0.9,"tr":0.3,"ed":-0.3,"sb":21,"sa":"21","sp":-1,"p":1,"l":99,"tf":2}
